[
  {
    "variant": "no_reuse_unitary",
    "synthesis": "unitary",
    "reuse": false,
    "N_sites": 10,
    "b_max": 2,
    "logical_qubits": 12,
    "high_level_depth": 11,
    "abstract_2q": 190,
    "abstract_depth": 697,
    "abstract_seconds": 0.015546731999961594,
    "device_2q": 376,
    "device_depth": 1339,
    "device_physical_qubits": 133,
    "device_qubits_used": 12,
    "device_seconds": 0.03238035399999717,
    "routing_inflation_2q": 1.979,
    "routing_overhead_2q": 186
  },
  {
    "variant": "no_reuse_isometry",
    "synthesis": "isometry",
    "reuse": false,
    "N_sites": 10,
    "b_max": 2,
    "logical_qubits": 12,
    "high_level_depth": 11,
    "abstract_2q": 164,
    "abstract_depth": 556,
    "abstract_seconds": 0.06779001999996126,
    "device_2q": 293,
    "device_depth": 1016,
    "device_physical_qubits": 133,
    "device_qubits_used": 12,
    "device_seconds": 0.08634476700001414,
    "routing_inflation_2q": 1.787,
    "routing_overhead_2q": 129
  },
  {
    "variant": "reuse_unitary",
    "synthesis": "unitary",
    "reuse": true,
    "N_sites": 10,
    "b_max": 2,
    "logical_qubits": 3,
    "high_level_depth": 29,
    "abstract_2q": 190,
    "abstract_depth": 758,
    "abstract_seconds": 0.00864076400000613,
    "device_2q": 270,
    "device_depth": 1208,
    "device_physical_qubits": 133,
    "device_qubits_used": 3,
    "device_seconds": 0.021390139999994062,
    "routing_inflation_2q": 1.421,
    "routing_overhead_2q": 80
  },
  {
    "variant": "reuse_isometry",
    "synthesis": "isometry",
    "reuse": true,
    "N_sites": 10,
    "b_max": 2,
    "logical_qubits": 3,
    "high_level_depth": 29,
    "abstract_2q": 164,
    "abstract_depth": 559,
    "abstract_seconds": 0.06211685000005218,
    "device_2q": 283,
    "device_depth": 1104,
    "device_physical_qubits": 133,
    "device_qubits_used": 3,
    "device_seconds": 0.08320256000001791,
    "routing_inflation_2q": 1.726,
    "routing_overhead_2q": 119
  }
]