[
  {
    "variant": "no_reuse_unitary",
    "synthesis": "unitary",
    "reuse": false,
    "N_sites": 12,
    "b_max": 2,
    "logical_qubits": 14,
    "high_level_depth": 13,
    "abstract_2q": 228,
    "abstract_depth": 838,
    "abstract_seconds": 0.01827608599998598,
    "device_2q": 450,
    "device_depth": 1589,
    "device_physical_qubits": 133,
    "device_qubits_used": 14,
    "device_seconds": 0.04061052500000528,
    "routing_inflation_2q": 1.974,
    "routing_overhead_2q": 222
  },
  {
    "variant": "no_reuse_isometry",
    "synthesis": "isometry",
    "reuse": false,
    "N_sites": 12,
    "b_max": 2,
    "logical_qubits": 14,
    "high_level_depth": 13,
    "abstract_2q": 205,
    "abstract_depth": 702,
    "abstract_seconds": 0.07988597900001082,
    "device_2q": 365,
    "device_depth": 1331,
    "device_physical_qubits": 133,
    "device_qubits_used": 14,
    "device_seconds": 0.11102495099999032,
    "routing_inflation_2q": 1.78,
    "routing_overhead_2q": 160
  },
  {
    "variant": "reuse_unitary",
    "synthesis": "unitary",
    "reuse": true,
    "N_sites": 12,
    "b_max": 2,
    "logical_qubits": 3,
    "high_level_depth": 35,
    "abstract_2q": 228,
    "abstract_depth": 912,
    "abstract_seconds": 0.00988663799998335,
    "device_2q": 328,
    "device_depth": 1464,
    "device_physical_qubits": 133,
    "device_qubits_used": 3,
    "device_seconds": 0.025334452999999257,
    "routing_inflation_2q": 1.439,
    "routing_overhead_2q": 100
  },
  {
    "variant": "reuse_isometry",
    "synthesis": "isometry",
    "reuse": true,
    "N_sites": 12,
    "b_max": 2,
    "logical_qubits": 3,
    "high_level_depth": 35,
    "abstract_2q": 205,
    "abstract_depth": 704,
    "abstract_seconds": 0.08150354099998935,
    "device_2q": 360,
    "device_depth": 1422,
    "device_physical_qubits": 133,
    "device_qubits_used": 3,
    "device_seconds": 0.10434217799999601,
    "routing_inflation_2q": 1.756,
    "routing_overhead_2q": 155
  }
]